parallel_bilby/.version
parallel_bilby/__init__.py
parallel_bilby/generation.py
parallel_bilby/schwimmbad_fast.py
parallel_bilby/utils.py
parallel_bilby/analysis/__init__.py
parallel_bilby/analysis/analysis_run.py
parallel_bilby/analysis/likelihood.py
parallel_bilby/analysis/main.py
parallel_bilby/analysis/plotting.py
parallel_bilby/analysis/read_write.py
parallel_bilby/analysis/sample_space.py
parallel_bilby/parser/__init__.py
parallel_bilby/parser/analysis.py
parallel_bilby/parser/generation.py
parallel_bilby/parser/shared.py
parallel_bilby/slurm/__init__.py
parallel_bilby/slurm/slurm.py
parallel_bilby/slurm/template_slurm.sh
parallel_bilby-2.0.2.dist-info/LICENSE
parallel_bilby-2.0.2.dist-info/METADATA
parallel_bilby-2.0.2.dist-info/WHEEL
parallel_bilby-2.0.2.dist-info/entry_points.txt
parallel_bilby-2.0.2.dist-info/top_level.txt
parallel_bilby-2.0.2.dist-info/RECORD
