Metadata-Version: 2.1
Name: parallel-bilby
Version: 2.0.2
Summary: Running bilby on GW data with MPI
Home-page: https://git.ligo.org/lscsoft/parallel_bilby
Author: pBilby Developers
Author-email: gregory.ashton@ligo.org
License: MIT
Classifier: Programming Language :: Python :: 3.8
Classifier: License :: OSI Approved :: MIT License
Classifier: Operating System :: MacOS :: MacOS X
Classifier: Operating System :: POSIX
Requires-Python: >=3.8
License-File: LICENSE
Requires-Dist: bilby (>=2.0.0)
Requires-Dist: bilby-pipe (>=1.0.7)
Requires-Dist: scipy (>=1.2.0)
Requires-Dist: gwpy (>=3.0.2)
Requires-Dist: matplotlib
Requires-Dist: numpy
Requires-Dist: tqdm
Requires-Dist: corner
Requires-Dist: dynesty (>=2)
Requires-Dist: schwimmbad
Requires-Dist: pandas
Requires-Dist: nestcheck
Requires-Dist: mpi4py (>3.0.0)
Requires-Dist: jinja2
Requires-Dist: dill
Provides-Extra: docs
Requires-Dist: sphinx ; extra == 'docs'
Requires-Dist: numpydoc ; extra == 'docs'
Requires-Dist: nbsphinx ; extra == 'docs'
Requires-Dist: sphinx-rtd-theme ; extra == 'docs'
Requires-Dist: sphinx-tabs ; extra == 'docs'
Requires-Dist: autodoc ; extra == 'docs'
Requires-Dist: sphinx-argparse ; extra == 'docs'
Requires-Dist: graphviz ; extra == 'docs'
Provides-Extra: test
Requires-Dist: mock ; extra == 'test'
Requires-Dist: deepdiff ; extra == 'test'
Requires-Dist: pytest-cov ; extra == 'test'
Requires-Dist: pytest-mpi ; extra == 'test'
